AlphaZeroCode/Agent.py
AlphaZeroCode/Evaluate.py
AlphaZeroCode/MCTS.py
AlphaZeroCode/Node.py
AlphaZeroCode/SelfPlay.py
AlphaZeroCode/Train.py
AlphaZeroCode/Util.py
AlphaZeroCode/__init__.py
AlphaZeroCode/env/TicTacToe.py
AlphaZeroCode/env/__init__.py
AlphaZeroCode/network/AlphaZeroNetwork.py
AlphaZeroCode/network/SimpleNet.py
AlphaZeroCode/network/__init__.py
alphazerocode-1.10.1.1.dist-info/METADATA
alphazerocode-1.10.1.1.dist-info/WHEEL
alphazerocode-1.10.1.1.dist-info/top_level.txt
alphazerocode-1.10.1.1.dist-info/RECORD
