Metadata-Version: 2.1
Name: alphazerocode
Version: 1.10.1.1
Summary: AlphaZeroCode
Author: M.Uchiyama
License: MIT
Keywords: AlphaZeroCode
Classifier: License :: OSI Approved :: MIT License
Classifier: Programming Language :: Python :: 3.10
